homecom/__init__.py
homecom/abstract_auth.py
homecom/air_conditioner.py
homecom/homecom_api.py
homecom/homecom_auth.py
homecom-0.1.4.dist-info/METADATA
homecom-0.1.4.dist-info/WHEEL
homecom-0.1.4.dist-info/RECORD
