Metadata-Version: 2.1
Name: homecom
Version: 0.1.4
Summary: 
License: MIT
Author: neugartf
Author-email: fabianneugart@gmail.com
Requires-Python: >=3.10,<4.0
Classifier: License :: OSI Approved :: MIT License
Classifier: Programming Language :: Python :: 3
Classifier: Programming Language :: Python :: 3.10
Classifier: Programming Language :: Python :: 3.11
Requires-Dist: StrEnum (>=0.4.8,<0.5.0)
Requires-Dist: aiohttp (>=3.8.1,<4.0.0)
Requires-Dist: lxml (>=4.9.1,<5.0.0)
Requires-Dist: pyppeteer (>=1.0.2,<2.0.0)
Requires-Dist: python-dotenv (>=0.21.0,<0.22.0)
